Workbook
Name Aporte: Ferramenta!$D$18
Name Patrimonio: Ferramenta!$D$21
Name Qtd_anos: Ferramenta!$D$19
Name Rendimento_Carteira: Ferramenta!$D$13
Name Salario: Ferramenta!$D$12
Name Sugestao_investimento: Ferramenta!$D$14
Name Taxa_mensal: Ferramenta!$D$20
Name total_investido_bolso: Ferramenta!$D$33

Sheet Ferramenta
B11: CONFIGURAÇÕES
B12: Salário | D12: 5000
B13: Rendimento Carteira | D13: 0.006
B14: Sugestão de Investimento (30%) | D14: =D12*30% -> 1500
B17: INVESTIMENTO MENSAL
B18: Quanto investir por mês? | D18: 1500
B19: Por quantos anos? | D19: 5
B20: Taxa de rendimento mensal? | D20: 0.01079
B21: Patrimônio acumulado? | D21: =FV(Taxa_mensal,Qtd_anos*12,Aporte*-1) -> 125665.37
B22: Dividendos mensais? | D22: =Patrimonio*Rendimento_Carteira -> 753.99223
B25: CENÁRIOS | D25: Dividendo
A26: 2 | B26: Quanto em 2 anos | C26: =FV(Taxa_mensal,$A26*12,Aporte*-1) -> 40841.441 | D26: =$C26*Rendimento_Carteira -> 245.04865
A27: 5 | B27: Quanto em 5 anos | C27: =FV(Taxa_mensal,$A27*12,Aporte*-1) -> 125665.37 | D27: =$C27*Rendimento_Carteira -> 753.99223
A28: 10 | B28: Quanto em 10 anos | C28: =FV(Taxa_mensal,$A28*12,Aporte*-1) -> 364926.32 | D28: =$C28*Rendimento_Carteira -> 2189.5579
A29: 20 | B29: Quanto em 20 anos | C29: =FV(Taxa_mensal,$A29*12,Aporte*-1) -> 1687797.6 | D29: =$C29*Rendimento_Carteira -> 10126.786
A30: 30 | B30: Quanto em 30 anos | C30: =FV(Taxa_mensal,$A30*12,Aporte*-1) -> 6483254.5 | D30: =$C30*Rendimento_Carteira -> 38899.527
B32: RESUMO DE RENDIMENTOS (30 ANOS)
B33: TOTAL INVESTIDO DO BOLSO | D33: =Aporte*30*12 -> 540000
B34: JUROS/DIVIDENDOS ACUMULADOS | D34: =C30-D33 -> 5943254.5
B35: PATRIMÔNIO TOTAL FINAL | D35: =C30 -> 6483254.5
B38: PERFIL | C38: AGRESSIVO
B39: VALOR A SER INVESTIDO POR MÊS | C39: =Aporte -> 1500
B41: TIPO DE FII | C41: PERCENTUAL SUGERIDO | D41: VALORES
B42: PAPEL | C42: =VLOOKUP($C$38&"-"&B42,Apoio!A:D,4,0) -> 0.5 | D42: =C42*$C$39 -> 750
B43: TIJOLO | C43: =VLOOKUP($C$38&"-"&B43,Apoio!A:D,4,0) -> 0.1 | D43: =C43*$C$39 -> 150
B44: HÍBRIDOS | C44: =VLOOKUP($C$38&"-"&B44,Apoio!A:D,4,0) -> 0.05 | D44: =C44*$C$39 -> 75
B45: FOFs | C45: =VLOOKUP($C$38&"-"&B45,Apoio!A:D,4,0) -> 0.05 | D45: =C45*$C$39 -> 75
B46: DESENVOLVIMENTO | C46: =VLOOKUP($C$38&"-"&B46,Apoio!A:D,4,0) -> 0.2 | D46: =C46*$C$39 -> 300
B47: HOTELARIAS | C47: =VLOOKUP($C$38&"-"&B47,Apoio!A:D,4,0) -> 0.1 | D47: =C47*$C$39 -> 150
D48: =SUM(D42:D47) -> 1500

Sheet Apoio
A2: CHAVE | B2: PERFIL | C2: TIPO DE FII | D2: %
A3: =B3&"-"&C3 -> CONSERVADOR-PAPEL | B3: CONSERVADOR | C3: PAPEL | D3: 0.3 | H3: %
A4: =B4&"-"&C4 -> CONSERVADOR-TIJOLO | B4: CONSERVADOR | C4: TIJOLO | D4: 0.5 | G4: MODERADO-TIJOLO | H4: =VLOOKUP($G$4,$A:$D,4,0) -> 0.35
A5: =B5&"-"&C5 -> CONSERVADOR-HÍBRIDOS | B5: CONSERVADOR | C5: HÍBRIDOS | D5: 0.1
A6: =B6&"-"&C6 -> CONSERVADOR-FOFs | B6: CONSERVADOR | C6: FOFs | D6: 0.1
A7: =B7&"-"&C7 -> CONSERVADOR-DESENVOLVIMENTO | B7: CONSERVADOR | C7: DESENVOLVIMENTO | D7: 0
A8: =B8&"-"&C8 -> CONSERVADOR-HOTELARIAS | B8: CONSERVADOR | C8: HOTELARIAS | D8: 0
A9: =B9&"-"&C9 -> MODERADO-PAPEL | B9: MODERADO | C9: PAPEL | D9: 0.32
A10: =B10&"-"&C10 -> MODERADO-TIJOLO | B10: MODERADO | C10: TIJOLO | D10: 0.35
A11: =B11&"-"&C11 -> MODERADO-HÍBRIDOS | B11: MODERADO | C11: HÍBRIDOS | D11: 0.08
A12: =B12&"-"&C12 -> MODERADO-FOFs | B12: MODERADO | C12: FOFs | D12: 0.05
A13: =B13&"-"&C13 -> MODERADO-DESENVOLVIMENTO | B13: MODERADO | C13: DESENVOLVIMENTO | D13: 0.1
A14: =B14&"-"&C14 -> MODERADO-HOTELARIAS | B14: MODERADO | C14: HOTELARIAS | D14: 0.1
A15: =B15&"-"&C15 -> AGRESSIVO-PAPEL | B15: AGRESSIVO | C15: PAPEL | D15: 0.5
A16: =B16&"-"&C16 -> AGRESSIVO-TIJOLO | B16: AGRESSIVO | C16: TIJOLO | D16: 0.1
... A20: =B20&"-"&C20 -> AGRESSIVO-HOTELARIAS | B20: AGRESSIVO | C20: HOTELARIAS | D20: 0.1
